neuropulse/S3Toolkit.py
neuropulse/__init__.py
neuropulse/main.py
neuropulse/utils.py
neuropulse-2.0.dist-info/LICENSE
neuropulse-2.0.dist-info/METADATA
neuropulse-2.0.dist-info/WHEEL
neuropulse-2.0.dist-info/top_level.txt
neuropulse-2.0.dist-info/RECORD
