Metadata-Version: 2.1
Name: neuropulse
Version: 2.0
Summary: A short description of the package
Home-page: https://github.com/jayaharisai/NeuroPulse.git
Author: Jayaharisai Tothala
Author-email: jayaharisai1212@gmail.com
Classifier: Programming Language :: Python :: 3
Classifier: License :: OSI Approved :: MIT License
Classifier: Operating System :: OS Independent
Requires-Python: >=3.6
License-File: LICENSE
Requires-Dist: boto3
